details/__init__.py
details/constant.py
details/data.py
details/run.py
uniadmin-1.0.0.dist-info/LICENSE
uniadmin-1.0.0.dist-info/METADATA
uniadmin-1.0.0.dist-info/WHEEL
uniadmin-1.0.0.dist-info/top_level.txt
uniadmin-1.0.0.dist-info/RECORD
